pyx402/__init__.py
pyx402/client.py
pyx402-0.1.0.dist-info/METADATA
pyx402-0.1.0.dist-info/WHEEL
pyx402-0.1.0.dist-info/RECORD
